tests/__init__.py
tests/test_cal.py
tests/test_fundamental_graphs.py
tests/test_ideas.py
tests/test_indicators.py
tests/test_market_movers.py
tests/test_markets.py
tests/test_minds.py
tests/test_news.py
tests/test_overview.py
tests/test_realtime_price.py
tests/test_screener.py
tests/test_streamer.py
tests/test_symbol_markets.py
tradingview_scraper/__init__.py
tradingview_scraper/tradingview_scraper.py
tradingview_scraper/data/areas.json
tradingview_scraper/data/exchanges.txt
tradingview_scraper/data/indicators.txt
tradingview_scraper/data/languages.json
tradingview_scraper/data/news_providers.txt
tradingview_scraper/data/timeframes.json
tradingview_scraper/symbols/__init__.py
tradingview_scraper/symbols/cal.py
tradingview_scraper/symbols/exceptions.py
tradingview_scraper/symbols/fundamental_graphs.py
tradingview_scraper/symbols/ideas.py
tradingview_scraper/symbols/market_movers.py
tradingview_scraper/symbols/markets.py
tradingview_scraper/symbols/minds.py
tradingview_scraper/symbols/news.py
tradingview_scraper/symbols/overview.py
tradingview_scraper/symbols/screener.py
tradingview_scraper/symbols/symbol_markets.py
tradingview_scraper/symbols/technicals.py
tradingview_scraper/symbols/utils.py
tradingview_scraper/symbols/stream/__init__.py
tradingview_scraper/symbols/stream/price.py
tradingview_scraper/symbols/stream/stream_handler.py
tradingview_scraper/symbols/stream/streamer.py
tradingview_scraper/symbols/stream/utils.py
tradingview_scraper/utils/__init__.py
tradingview_scraper-0.4.20.dist-info/licenses/LICENSE
tradingview_scraper-0.4.20.dist-info/METADATA
tradingview_scraper-0.4.20.dist-info/WHEEL
tradingview_scraper-0.4.20.dist-info/top_level.txt
tradingview_scraper-0.4.20.dist-info/RECORD
