Metadata-Version: 2.4
Name: tradingview-scraper
Version: 0.4.20
Summary: Tradingview scraper tool
Home-page: https://github.com/mnwato/tradingview-scraper
Download-URL: https://github.com/mnwato/tradingview-scraper/archive/refs/tags/0.4.9.zip
Author: Mostafa Najmi
Author-email: m.n.irib@gmail.com
License: MIT
Keywords: tradingview,scraper,python,crawler,financial
Classifier: Development Status :: 2 - Pre-Alpha
Classifier: Intended Audience :: Developers
Classifier: Operating System :: OS Independent
Classifier: License :: OSI Approved :: MIT License
Classifier: Programming Language :: Python :: 3.8
License-File: LICENSE
Requires-Dist: setuptools
Requires-Dist: requests==2.32.4
Requires-Dist: pandas>=2.0.3
Requires-Dist: beautifulsoup4>=4.12.3
Requires-Dist: pydantic>=2.8.2
Requires-Dist: websockets>=13.1
Requires-Dist: websocket-client>=1.8.0
Requires-Dist: python-dotenv>=1.0.1
Dynamic: author
Dynamic: author-email
Dynamic: classifier
Dynamic: description
Dynamic: description-content-type
Dynamic: download-url
Dynamic: home-page
Dynamic: keywords
Dynamic: license
Dynamic: license-file
Dynamic: requires-dist
Dynamic: summary
